[
    {
      "_id": { "$oid": "64392d39dfd90fb29e464fb7" },
      "title": "Sunny Meadow Cottage",
      "description": "A cozy cottage in the heart of the countryside, offering serene views and a peaceful retreat.",
      "price": 5000,
      "address": "101 Countryside Lane",
      "city": "Austin",
      "country": "US",
      "image": "https://example.com/image1.jpg",
      "userEmail": "user@example.com",
      "createdAt": { "$date": "2024-03-01T10:38:48.762Z" },
      "updatedAt": { "$date": "2024-03-02T10:38:48.762Z" },
      "facilities": { "bathrooms": "2", "parking": "2", "bedrooms": "3" }
    },
    {
      "_id": { "$oid": "64392e0bdfd90fb29e464fbc" },
      "title": "Urban Dream Loft",
      "description": "Modern and stylish loft in the vibrant heart of the city, close to all amenities.",
      "price": 7000,
      "address": "202 Cityscape Blvd",
      "city": "San Francisco",
      "country": "US",
      "image": "https://example.com/image2.jpg",
      "userEmail": "loftowner@example.com",
      "createdAt": { "$date": "2024-03-03T10:42:19.231Z" },
      "updatedAt": { "$date": "2024-03-04T10:42:19.231Z" },
      "facilities": { "bathrooms": "1", "parking": "1", "bedrooms": "2" }
    },
    {
      "_id": { "$oid": "6439001c74446601d6fce96d" },
      "title": "Lakeside Villa",
      "description": "Breathtaking lakeside villa with private dock and expansive outdoor entertaining areas.",
      "price": 12000,
      "address": "303 Lakeshore Drive",
      "city": "Seattle",
      "country": "US",
      "image": "https://example.com/image3.jpg",
      "userEmail": "lakehouse@example.com",
      "createdAt": { "$date": "2024-03-05T07:26:20.051Z" },
      "updatedAt": { "$date": "2024-03-06T07:26:20.051Z" },
      "facilities": { "bathrooms": "4", "parking": "3", "bedrooms": "5" }
    },
    {
      "_id": { "$oid": "64392e1edfd90fb29e464fbd" },
      "title": "Mountain Retreat",
      "description": "Secluded mountain retreat with stunning views and luxurious amenities.",
      "price": 8500,
      "address": "404 Mountain Peak Road",
      "city": "Denver",
      "country": "US",
      "image": "https://example.com/image4.jpg",
      "userEmail": "retreatowner@example.com",
      "createdAt": { "$date": "2024-03-07T10:42:37.946Z" },
      "updatedAt": { "$date": "2024-03-08T10:42:37.946Z" },
      "facilities": { "bathrooms": "3", "parking": "2", "bedrooms": "4" }
    },
    {
        "_id": { "$oid": "64392e69dfd90fb29e464fc1" },
        "title": "Coastal Escape Condo",
        "description": "A stunning condo overlooking the ocean, with access to private beaches and top-notch amenities.",
        "price": 6000,
        "address": "505 Seaside Avenue",
        "city": "Miami",
        "country": "US",
        "image": "https://example.com/image5.jpg",
        "userEmail": "condoowner@example.com",
        "createdAt": { "$date": "2024-03-09T10:43:53.665Z" },
        "updatedAt": { "$date": "2024-03-10T10:43:53.665Z" },
        "facilities": { "bathrooms": "2", "parking": "1", "bedrooms": "2" }
      },
      {
        "_id": { "$oid": "643a30b60c4348510952923a" },
        "title": "Downtown High-rise",
        "description": "Live above it all in this high-rise apartment located in the heart of downtown, offering spectacular city views.",
        "price": 5500,
        "address": "606 Urban Core Dr",
        "city": "Chicago",
        "country": "US",
        "image": "https://example.com/image6.jpg",
        "userEmail": "highriseowner@example.com",
        "createdAt": { "$date": "2024-03-11T05:05:58.189Z" },
        "updatedAt": { "$date": "2024-03-12T05:05:58.189Z" },
        "facilities": { "bathrooms": "2", "parking": "2", "bedrooms": "3" }
      },
      {
        "_id": { "$oid": "643900fa74446601d6fce96e" },
        "title": "Suburban Family Home",
        "description": "A spacious and comfortable home in a friendly suburban neighborhood, perfect for families looking for a quiet life.",
        "price": 4500,
        "address": "707 Suburbia Lane",
        "city": "Dallas",
        "country": "US",
        "image": "https://example.com/image7.jpg",
        "userEmail": "familyhomeowner@example.com",
        "createdAt": { "$date": "2024-03-13T07:29:58.262Z" },
        "updatedAt": { "$date": "2024-03-14T07:29:58.262Z" },
        "facilities": { "bathrooms": "3", "parking": "2", "bedrooms": "4" }
      },
      {
        "_id": { "$oid": "6439011d74446601d6fce96f" },
        "title": "Historic Downtown Loft",
        "description": "A beautifully renovated loft in a historic downtown building, featuring exposed brick and original wood floors.",
        "price": 6700,
        "address": "808 Heritage Rd",
        "city": "New Orleans",
        "country": "US",
        "image": "https://example.com/image8.jpg",
        "userEmail": "loftlover@example.com",
        "createdAt": { "$date": "2024-03-15T07:30:36.761Z" },
        "updatedAt": { "$date": "2024-03-16T07:30:36.761Z" },
        "facilities": { "bathrooms": "1", "parking": "None", "bedrooms": "2" }
      },
      {
        "_id": { "$oid": "64392ddddfd90fb29e464fba" },
        "title": "Rustic Mountain Cabin",
        "description": "Escape to the mountains in this rustic cabin, surrounded by nature and offering unmatched tranquility.",
        "price": 3800,
        "address": "909 Pinecrest Path",
        "city": "Aspen",
        "country": "US",
        "image": "https://example.com/image9.jpg",
        "userEmail": "cabinenthusiast@example.com",
        "createdAt": { "$date": "2024-03-17T10:41:32.998Z" },
        "updatedAt": { "$date": "2024-03-18T10:41:32.998Z" },
        "facilities": { "bathrooms": "2", "parking": "Available", "bedrooms": "3" }
      }     
]
  